<?xml version="1.0" encoding="UTF-8" ?>
<!DOCTYPE mapper PUBLIC "-//mybatis.org//DTD Mapper 3.0//EN" "http://mybatis.org/dtd/mybatis-3-mapper.dtd" >
<mapper namespace="jp.co.necsoft.web_md.core.common.mybatis.dao.Sc10eblgMapper" >
  <resultMap id="BaseResultMap" type="jp.co.necsoft.web_md.core.common.mybatis.dto.Sc10eblg" >
    <!--
      WARNING - @mbggenerated
      This element is automatically generated by MyBatis Generator, do not modify.
      This element was generated on Wed Jan 22 09:53:12 JST 2014.
    -->
    <result column="REQUEST_ID" property="requestId" jdbcType="VARCHAR" />
    <result column="CLASS_NAME" property="className" jdbcType="VARCHAR" />
    <result column="METHOD_NAME" property="methodName" jdbcType="VARCHAR" />
    <result column="TERM_IPADRESS" property="termIpadress" jdbcType="VARCHAR" />
    <result column="SERVER_NAME" property="serverName" jdbcType="VARCHAR" />
    <result column="SDATE" property="sdate" jdbcType="VARCHAR" />
    <result column="STIME" property="stime" jdbcType="VARCHAR" />
    <result column="PROCESS_TIME" property="processTime" jdbcType="DECIMAL" />
    <result column="LOG_TIME" property="logTime" jdbcType="DECIMAL" />
  </resultMap>
  <sql id="Example_Where_Clause" >
    <!--
      WARNING - @mbggenerated
      This element is automatically generated by MyBatis Generator, do not modify.
      This element was generated on Wed Jan 22 09:53:12 JST 2014.
    -->
    <where >
      <foreach collection="oredCriteria" item="criteria" separator="or" >
        <if test="criteria.valid" >
          <trim prefix="(" suffix=")" prefixOverrides="and" >
            <foreach collection="criteria.criteria" item="criterion" >
              <choose >
                <when test="criterion.noValue" >
                  and ${criterion.condition}
                </when>
                <when test="criterion.singleValue" >
                  and ${criterion.condition} #{criterion.value}
                </when>
                <when test="criterion.betweenValue" >
                  and ${criterion.condition} #{criterion.value} and #{criterion.secondValue}
                </when>
                <when test="criterion.listValue" >
                  and ${criterion.condition}
                  <foreach collection="criterion.value" item="listItem" open="(" close=")" separator="," >
                    #{listItem}
                  </foreach>
                </when>
              </choose>
            </foreach>
          </trim>
        </if>
      </foreach>
    </where>
  </sql>
  <sql id="Update_By_Example_Where_Clause" >
    <!--
      WARNING - @mbggenerated
      This element is automatically generated by MyBatis Generator, do not modify.
      This element was generated on Wed Jan 22 09:53:12 JST 2014.
    -->
    <where >
      <foreach collection="example.oredCriteria" item="criteria" separator="or" >
        <if test="criteria.valid" >
          <trim prefix="(" suffix=")" prefixOverrides="and" >
            <foreach collection="criteria.criteria" item="criterion" >
              <choose >
                <when test="criterion.noValue" >
                  and ${criterion.condition}
                </when>
                <when test="criterion.singleValue" >
                  and ${criterion.condition} #{criterion.value}
                </when>
                <when test="criterion.betweenValue" >
                  and ${criterion.condition} #{criterion.value} and #{criterion.secondValue}
                </when>
                <when test="criterion.listValue" >
                  and ${criterion.condition}
                  <foreach collection="criterion.value" item="listItem" open="(" close=")" separator="," >
                    #{listItem}
                  </foreach>
                </when>
              </choose>
            </foreach>
          </trim>
        </if>
      </foreach>
    </where>
  </sql>
  <sql id="Base_Column_List" >
    <!--
      WARNING - @mbggenerated
      This element is automatically generated by MyBatis Generator, do not modify.
      This element was generated on Wed Jan 22 09:53:12 JST 2014.
    -->
    REQUEST_ID, CLASS_NAME, METHOD_NAME, TERM_IPADRESS, SERVER_NAME, SDATE, STIME, PROCESS_TIME, 
    LOG_TIME
  </sql>
  <select id="selectByExample" resultMap="BaseResultMap" parameterType="jp.co.necsoft.web_md.core.common.mybatis.dto.Sc10eblgExample" >
    <!--
      WARNING - @mbggenerated
      This element is automatically generated by MyBatis Generator, do not modify.
      This element was generated on Wed Jan 22 09:53:12 JST 2014.
    -->
    select
    <if test="distinct" >
      distinct
    </if>
    <include refid="Base_Column_List" />
    from SC10EBLG
    <if test="_parameter != null" >
      <include refid="Example_Where_Clause" />
    </if>
    <if test="orderByClause != null" >
      order by ${orderByClause}
    </if>
  </select>
  <delete id="deleteByExample" parameterType="jp.co.necsoft.web_md.core.common.mybatis.dto.Sc10eblgExample" >
    <!--
      WARNING - @mbggenerated
      This element is automatically generated by MyBatis Generator, do not modify.
      This element was generated on Wed Jan 22 09:53:12 JST 2014.
    -->
    delete from SC10EBLG
    <if test="_parameter != null" >
      <include refid="Example_Where_Clause" />
    </if>
  </delete>
  <insert id="insert" parameterType="jp.co.necsoft.web_md.core.common.mybatis.dto.Sc10eblg" >
    <!--
      WARNING - @mbggenerated
      This element is automatically generated by MyBatis Generator, do not modify.
      This element was generated on Wed Jan 22 09:53:12 JST 2014.
    -->
    insert into SC10EBLG (REQUEST_ID, CLASS_NAME, METHOD_NAME, 
      TERM_IPADRESS, SERVER_NAME, SDATE, 
      STIME, PROCESS_TIME, LOG_TIME
      )
    values (#{requestId,jdbcType=VARCHAR}, #{className,jdbcType=VARCHAR}, #{methodName,jdbcType=VARCHAR}, 
      #{termIpadress,jdbcType=VARCHAR}, #{serverName,jdbcType=VARCHAR}, #{sdate,jdbcType=VARCHAR}, 
      #{stime,jdbcType=VARCHAR}, #{processTime,jdbcType=DECIMAL}, #{logTime,jdbcType=DECIMAL}
      )
  </insert>
  <insert id="insertSelective" parameterType="jp.co.necsoft.web_md.core.common.mybatis.dto.Sc10eblg" >
    <!--
      WARNING - @mbggenerated
      This element is automatically generated by MyBatis Generator, do not modify.
      This element was generated on Wed Jan 22 09:53:12 JST 2014.
    -->
    insert into SC10EBLG
    <trim prefix="(" suffix=")" suffixOverrides="," >
      <if test="requestId != null" >
        REQUEST_ID,
      </if>
      <if test="className != null" >
        CLASS_NAME,
      </if>
      <if test="methodName != null" >
        METHOD_NAME,
      </if>
      <if test="termIpadress != null" >
        TERM_IPADRESS,
      </if>
      <if test="serverName != null" >
        SERVER_NAME,
      </if>
      <if test="sdate != null" >
        SDATE,
      </if>
      <if test="stime != null" >
        STIME,
      </if>
      <if test="processTime != null" >
        PROCESS_TIME,
      </if>
      <if test="logTime != null" >
        LOG_TIME,
      </if>
    </trim>
    <trim prefix="values (" suffix=")" suffixOverrides="," >
      <if test="requestId != null" >
        #{requestId,jdbcType=VARCHAR},
      </if>
      <if test="className != null" >
        #{className,jdbcType=VARCHAR},
      </if>
      <if test="methodName != null" >
        #{methodName,jdbcType=VARCHAR},
      </if>
      <if test="termIpadress != null" >
        #{termIpadress,jdbcType=VARCHAR},
      </if>
      <if test="serverName != null" >
        #{serverName,jdbcType=VARCHAR},
      </if>
      <if test="sdate != null" >
        #{sdate,jdbcType=VARCHAR},
      </if>
      <if test="stime != null" >
        #{stime,jdbcType=VARCHAR},
      </if>
      <if test="processTime != null" >
        #{processTime,jdbcType=DECIMAL},
      </if>
      <if test="logTime != null" >
        #{logTime,jdbcType=DECIMAL},
      </if>
    </trim>
  </insert>
  <select id="countByExample" parameterType="jp.co.necsoft.web_md.core.common.mybatis.dto.Sc10eblgExample" resultType="java.lang.Integer" >
    <!--
      WARNING - @mbggenerated
      This element is automatically generated by MyBatis Generator, do not modify.
      This element was generated on Wed Jan 22 09:53:12 JST 2014.
    -->
    select count(*) from SC10EBLG
    <if test="_parameter != null" >
      <include refid="Example_Where_Clause" />
    </if>
  </select>
  <update id="updateByExampleSelective" parameterType="map" >
    <!--
      WARNING - @mbggenerated
      This element is automatically generated by MyBatis Generator, do not modify.
      This element was generated on Wed Jan 22 09:53:12 JST 2014.
    -->
    update SC10EBLG
    <set >
      <if test="record.requestId != null" >
        REQUEST_ID = #{record.requestId,jdbcType=VARCHAR},
      </if>
      <if test="record.className != null" >
        CLASS_NAME = #{record.className,jdbcType=VARCHAR},
      </if>
      <if test="record.methodName != null" >
        METHOD_NAME = #{record.methodName,jdbcType=VARCHAR},
      </if>
      <if test="record.termIpadress != null" >
        TERM_IPADRESS = #{record.termIpadress,jdbcType=VARCHAR},
      </if>
      <if test="record.serverName != null" >
        SERVER_NAME = #{record.serverName,jdbcType=VARCHAR},
      </if>
      <if test="record.sdate != null" >
        SDATE = #{record.sdate,jdbcType=VARCHAR},
      </if>
      <if test="record.stime != null" >
        STIME = #{record.stime,jdbcType=VARCHAR},
      </if>
      <if test="record.processTime != null" >
        PROCESS_TIME = #{record.processTime,jdbcType=DECIMAL},
      </if>
      <if test="record.logTime != null" >
        LOG_TIME = #{record.logTime,jdbcType=DECIMAL},
      </if>
    </set>
    <if test="_parameter != null" >
      <include refid="Update_By_Example_Where_Clause" />
    </if>
  </update>
  <update id="updateByExample" parameterType="map" >
    <!--
      WARNING - @mbggenerated
      This element is automatically generated by MyBatis Generator, do not modify.
      This element was generated on Wed Jan 22 09:53:12 JST 2014.
    -->
    update SC10EBLG
    set REQUEST_ID = #{record.requestId,jdbcType=VARCHAR},
      CLASS_NAME = #{record.className,jdbcType=VARCHAR},
      METHOD_NAME = #{record.methodName,jdbcType=VARCHAR},
      TERM_IPADRESS = #{record.termIpadress,jdbcType=VARCHAR},
      SERVER_NAME = #{record.serverName,jdbcType=VARCHAR},
      SDATE = #{record.sdate,jdbcType=VARCHAR},
      STIME = #{record.stime,jdbcType=VARCHAR},
      PROCESS_TIME = #{record.processTime,jdbcType=DECIMAL},
      LOG_TIME = #{record.logTime,jdbcType=DECIMAL}
    <if test="_parameter != null" >
      <include refid="Update_By_Example_Where_Clause" />
    </if>
  </update>
</mapper>