<?xml version="1.0" encoding="UTF-8" ?>
<!DOCTYPE mapper PUBLIC "-//mybatis.org//DTD Mapper 3.0//EN" "http://mybatis.org/dtd/mybatis-3-mapper.dtd" >
<mapper namespace="jp.co.necsoft.web_md.core.common.mybatis.dao.Sc77gmlgMapper" >
  <resultMap id="BaseResultMap" type="jp.co.necsoft.web_md.core.common.mybatis.dto.Sc77gmlg" >
    <!--
      WARNING - @mbggenerated
      This element is automatically generated by MyBatis Generator, do not modify.
      This element was generated on Wed Jan 22 09:53:12 JST 2014.
    -->
    <result column="SDATE" property="sdate" jdbcType="VARCHAR" />
    <result column="GAMEN_ID" property="gamenId" jdbcType="VARCHAR" />
    <result column="START_TIME" property="startTime" jdbcType="VARCHAR" />
    <result column="END_TIME" property="endTime" jdbcType="VARCHAR" />
    <result column="TERM_ID" property="termId" jdbcType="VARCHAR" />
    <result column="TERM_IPADRESS" property="termIpadress" jdbcType="VARCHAR" />
    <result column="TANTO_CD" property="tantoCd" jdbcType="VARCHAR" />
    <result column="FASE_NUM" property="faseNum" jdbcType="VARCHAR" />
    <result column="SYORI_KBN" property="syoriKbn" jdbcType="VARCHAR" />
    <result column="STIME" property="stime" jdbcType="DECIMAL" />
  </resultMap>
  <sql id="Example_Where_Clause" >
    <!--
      WARNING - @mbggenerated
      This element is automatically generated by MyBatis Generator, do not modify.
      This element was generated on Wed Jan 22 09:53:12 JST 2014.
    -->
    <where >
      <foreach collection="oredCriteria" item="criteria" separator="or" >
        <if test="criteria.valid" >
          <trim prefix="(" suffix=")" prefixOverrides="and" >
            <foreach collection="criteria.criteria" item="criterion" >
              <choose >
                <when test="criterion.noValue" >
                  and ${criterion.condition}
                </when>
                <when test="criterion.singleValue" >
                  and ${criterion.condition} #{criterion.value}
                </when>
                <when test="criterion.betweenValue" >
                  and ${criterion.condition} #{criterion.value} and #{criterion.secondValue}
                </when>
                <when test="criterion.listValue" >
                  and ${criterion.condition}
                  <foreach collection="criterion.value" item="listItem" open="(" close=")" separator="," >
                    #{listItem}
                  </foreach>
                </when>
              </choose>
            </foreach>
          </trim>
        </if>
      </foreach>
    </where>
  </sql>
  <sql id="Update_By_Example_Where_Clause" >
    <!--
      WARNING - @mbggenerated
      This element is automatically generated by MyBatis Generator, do not modify.
      This element was generated on Wed Jan 22 09:53:12 JST 2014.
    -->
    <where >
      <foreach collection="example.oredCriteria" item="criteria" separator="or" >
        <if test="criteria.valid" >
          <trim prefix="(" suffix=")" prefixOverrides="and" >
            <foreach collection="criteria.criteria" item="criterion" >
              <choose >
                <when test="criterion.noValue" >
                  and ${criterion.condition}
                </when>
                <when test="criterion.singleValue" >
                  and ${criterion.condition} #{criterion.value}
                </when>
                <when test="criterion.betweenValue" >
                  and ${criterion.condition} #{criterion.value} and #{criterion.secondValue}
                </when>
                <when test="criterion.listValue" >
                  and ${criterion.condition}
                  <foreach collection="criterion.value" item="listItem" open="(" close=")" separator="," >
                    #{listItem}
                  </foreach>
                </when>
              </choose>
            </foreach>
          </trim>
        </if>
      </foreach>
    </where>
  </sql>
  <sql id="Base_Column_List" >
    <!--
      WARNING - @mbggenerated
      This element is automatically generated by MyBatis Generator, do not modify.
      This element was generated on Wed Jan 22 09:53:12 JST 2014.
    -->
    SDATE, GAMEN_ID, START_TIME, END_TIME, TERM_ID, TERM_IPADRESS, TANTO_CD, FASE_NUM, 
    SYORI_KBN, STIME
  </sql>
  <select id="selectByExample" resultMap="BaseResultMap" parameterType="jp.co.necsoft.web_md.core.common.mybatis.dto.Sc77gmlgExample" >
    <!--
      WARNING - @mbggenerated
      This element is automatically generated by MyBatis Generator, do not modify.
      This element was generated on Wed Jan 22 09:53:12 JST 2014.
    -->
    select
    <if test="distinct" >
      distinct
    </if>
    <include refid="Base_Column_List" />
    from SC77GMLG
    <if test="_parameter != null" >
      <include refid="Example_Where_Clause" />
    </if>
    <if test="orderByClause != null" >
      order by ${orderByClause}
    </if>
  </select>
  <delete id="deleteByExample" parameterType="jp.co.necsoft.web_md.core.common.mybatis.dto.Sc77gmlgExample" >
    <!--
      WARNING - @mbggenerated
      This element is automatically generated by MyBatis Generator, do not modify.
      This element was generated on Wed Jan 22 09:53:12 JST 2014.
    -->
    delete from SC77GMLG
    <if test="_parameter != null" >
      <include refid="Example_Where_Clause" />
    </if>
  </delete>
  <insert id="insert" parameterType="jp.co.necsoft.web_md.core.common.mybatis.dto.Sc77gmlg" >
    <!--
      WARNING - @mbggenerated
      This element is automatically generated by MyBatis Generator, do not modify.
      This element was generated on Wed Jan 22 09:53:12 JST 2014.
    -->
    insert into SC77GMLG (SDATE, GAMEN_ID, START_TIME, 
      END_TIME, TERM_ID, TERM_IPADRESS, 
      TANTO_CD, FASE_NUM, SYORI_KBN, 
      STIME)
    values (#{sdate,jdbcType=VARCHAR}, #{gamenId,jdbcType=VARCHAR}, #{startTime,jdbcType=VARCHAR}, 
      #{endTime,jdbcType=VARCHAR}, #{termId,jdbcType=VARCHAR}, #{termIpadress,jdbcType=VARCHAR}, 
      #{tantoCd,jdbcType=VARCHAR}, #{faseNum,jdbcType=VARCHAR}, #{syoriKbn,jdbcType=VARCHAR}, 
      #{stime,jdbcType=DECIMAL})
  </insert>
  <insert id="insertSelective" parameterType="jp.co.necsoft.web_md.core.common.mybatis.dto.Sc77gmlg" >
    <!--
      WARNING - @mbggenerated
      This element is automatically generated by MyBatis Generator, do not modify.
      This element was generated on Wed Jan 22 09:53:12 JST 2014.
    -->
    insert into SC77GMLG
    <trim prefix="(" suffix=")" suffixOverrides="," >
      <if test="sdate != null" >
        SDATE,
      </if>
      <if test="gamenId != null" >
        GAMEN_ID,
      </if>
      <if test="startTime != null" >
        START_TIME,
      </if>
      <if test="endTime != null" >
        END_TIME,
      </if>
      <if test="termId != null" >
        TERM_ID,
      </if>
      <if test="termIpadress != null" >
        TERM_IPADRESS,
      </if>
      <if test="tantoCd != null" >
        TANTO_CD,
      </if>
      <if test="faseNum != null" >
        FASE_NUM,
      </if>
      <if test="syoriKbn != null" >
        SYORI_KBN,
      </if>
      <if test="stime != null" >
        STIME,
      </if>
    </trim>
    <trim prefix="values (" suffix=")" suffixOverrides="," >
      <if test="sdate != null" >
        #{sdate,jdbcType=VARCHAR},
      </if>
      <if test="gamenId != null" >
        #{gamenId,jdbcType=VARCHAR},
      </if>
      <if test="startTime != null" >
        #{startTime,jdbcType=VARCHAR},
      </if>
      <if test="endTime != null" >
        #{endTime,jdbcType=VARCHAR},
      </if>
      <if test="termId != null" >
        #{termId,jdbcType=VARCHAR},
      </if>
      <if test="termIpadress != null" >
        #{termIpadress,jdbcType=VARCHAR},
      </if>
      <if test="tantoCd != null" >
        #{tantoCd,jdbcType=VARCHAR},
      </if>
      <if test="faseNum != null" >
        #{faseNum,jdbcType=VARCHAR},
      </if>
      <if test="syoriKbn != null" >
        #{syoriKbn,jdbcType=VARCHAR},
      </if>
      <if test="stime != null" >
        #{stime,jdbcType=DECIMAL},
      </if>
    </trim>
  </insert>
  <select id="countByExample" parameterType="jp.co.necsoft.web_md.core.common.mybatis.dto.Sc77gmlgExample" resultType="java.lang.Integer" >
    <!--
      WARNING - @mbggenerated
      This element is automatically generated by MyBatis Generator, do not modify.
      This element was generated on Wed Jan 22 09:53:12 JST 2014.
    -->
    select count(*) from SC77GMLG
    <if test="_parameter != null" >
      <include refid="Example_Where_Clause" />
    </if>
  </select>
  <update id="updateByExampleSelective" parameterType="map" >
    <!--
      WARNING - @mbggenerated
      This element is automatically generated by MyBatis Generator, do not modify.
      This element was generated on Wed Jan 22 09:53:12 JST 2014.
    -->
    update SC77GMLG
    <set >
      <if test="record.sdate != null" >
        SDATE = #{record.sdate,jdbcType=VARCHAR},
      </if>
      <if test="record.gamenId != null" >
        GAMEN_ID = #{record.gamenId,jdbcType=VARCHAR},
      </if>
      <if test="record.startTime != null" >
        START_TIME = #{record.startTime,jdbcType=VARCHAR},
      </if>
      <if test="record.endTime != null" >
        END_TIME = #{record.endTime,jdbcType=VARCHAR},
      </if>
      <if test="record.termId != null" >
        TERM_ID = #{record.termId,jdbcType=VARCHAR},
      </if>
      <if test="record.termIpadress != null" >
        TERM_IPADRESS = #{record.termIpadress,jdbcType=VARCHAR},
      </if>
      <if test="record.tantoCd != null" >
        TANTO_CD = #{record.tantoCd,jdbcType=VARCHAR},
      </if>
      <if test="record.faseNum != null" >
        FASE_NUM = #{record.faseNum,jdbcType=VARCHAR},
      </if>
      <if test="record.syoriKbn != null" >
        SYORI_KBN = #{record.syoriKbn,jdbcType=VARCHAR},
      </if>
      <if test="record.stime != null" >
        STIME = #{record.stime,jdbcType=DECIMAL},
      </if>
    </set>
    <if test="_parameter != null" >
      <include refid="Update_By_Example_Where_Clause" />
    </if>
  </update>
  <update id="updateByExample" parameterType="map" >
    <!--
      WARNING - @mbggenerated
      This element is automatically generated by MyBatis Generator, do not modify.
      This element was generated on Wed Jan 22 09:53:12 JST 2014.
    -->
    update SC77GMLG
    set SDATE = #{record.sdate,jdbcType=VARCHAR},
      GAMEN_ID = #{record.gamenId,jdbcType=VARCHAR},
      START_TIME = #{record.startTime,jdbcType=VARCHAR},
      END_TIME = #{record.endTime,jdbcType=VARCHAR},
      TERM_ID = #{record.termId,jdbcType=VARCHAR},
      TERM_IPADRESS = #{record.termIpadress,jdbcType=VARCHAR},
      TANTO_CD = #{record.tantoCd,jdbcType=VARCHAR},
      FASE_NUM = #{record.faseNum,jdbcType=VARCHAR},
      SYORI_KBN = #{record.syoriKbn,jdbcType=VARCHAR},
      STIME = #{record.stime,jdbcType=DECIMAL}
    <if test="_parameter != null" >
      <include refid="Update_By_Example_Where_Clause" />
    </if>
  </update>
</mapper>